{"sample":{"expires":"never","id":"sample","promoter":"Community Spotlight","promoter-url":"https://github.com/Community-Spotlight","tags":["gaming","art","technology","music","entertainment"],"media":{"images":[{"size":"250x250","type":"svg"},{"size":"300x250","type":"svg"},{"size":"120x360","type":"svg"},{"size":"360x120","type":"svg"},{"size":"300x50","type":"svg"},{"size":"50x300","type":"svg"},{"size":"480x270","type":"svg"}],"videos":[{"size":"4:3","length":5,"type":"mp4"}],"htmls":[]}},"u9^(5{Ke=uwX7!l":{"id":"u9^(5{Ke=uwX7!l","expires":1737845219266,"promoter":"SnowShare","promoter-url":"https://discord.gg/XKbuEFDf2x","tags":["Gaming","Art","Music","Technology","Entertainment","English","Humor","Lifestyle"],"media":{"images":[{"size":"300x50","type":"png"},{"size":"120x360","type":"png"},{"size":"360x120","type":"png"}],"videos":[],"htmls":[]}},"X[8VsD+i4h^F-#s":{"id":"X[8VsD+i4h^F-#s","expires":1738135299316,"promoter":"Candy for Life","promoter-url":"https://slepstudios.itch.io/candyforlife","tags":["Gaming","Dark Mode","Light Mode","English"],"media":{"images":[{"size":"250x250","type":"png"}],"videos":[],"htmls":[]}},"5jvSc!R5JjPvFIu":{"id":"5jvSc!R5JjPvFIu","expires":1738363369399,"promoter":"TurboButterfly: Bluesky API for Turbowarp","promoter-url":"https://github.com/hammouda101010/turbowarp-bsky-api","tags":["Technology","English","Culture"],"media":{"images":[{"size":"360x120","type":"png"},{"size":"250x250","type":"png"}],"videos":[],"htmls":[]}},"5*oqZdwf)3)#WtM":{"id":"5*oqZdwf)3)#WtM","expires":1738386385649,"promoter":"Death2Life Suicide Hotline","promoter-url":"https://d2lrevolution.com/?gad_source=1&gclid=CjwKCAiAnKi8BhB0EiwA58DA4QIIEHOfUKGY9W4l5WwR6Z4uljsACuyLKR7ktxulqCHEVW6a-FmvyhoCniQQAvD_BwE","tags":["Health","Dark Mode","English"],"media":{"images":[{"size":"250x250","type":"png"}],"videos":[],"htmls":[]}}}
